mulib/__init__.py
mulib/cl.py
mylib_fl44_1-0.1.2.dist-info/METADATA
mylib_fl44_1-0.1.2.dist-info/WHEEL
mylib_fl44_1-0.1.2.dist-info/top_level.txt
mylib_fl44_1-0.1.2.dist-info/RECORD
