Metadata-Version: 2.4
Name: mylib_fl44_1
Version: 0.1.2
Summary: My Python cheat sheet library for quick reference
Author-email: Your Name <you@example.com>
License: MIT
Requires-Python: >=3.7
